pyNNRW/__init__.py
pyNNRW/aerw.py
pyNNRW/dtc.py
pyNNRW/elm.py
pyNNRW/knn.py
pyNNRW/knnrw.py
pyNNRW/lr.py
pyNNRW/mlp.py
pyNNRW/nnrw.py
pyNNRW/rbfnn.py
pyNNRW/rbm.py
pyNNRW/rvfl.py
pyNNRW/wann.py
pyNNRW-0.3.5.dist-info/LICENCE
pyNNRW-0.3.5.dist-info/METADATA
pyNNRW-0.3.5.dist-info/WHEEL
pyNNRW-0.3.5.dist-info/top_level.txt
pyNNRW-0.3.5.dist-info/RECORD
